Workbook

Sheet Raw_Actuals
A1: Years | B1: 2018 | C1: 2019 | D1: 2020 | E1: 2021 | F1: 2022 | G1: 2023 | H1: 2024 | I1: 2025
A2: Revenue | B2: 265595 | C2: 260174 | D2: 274515 | E2: 365817 | F2: 394328 | G2: 383285 | H2: 385603 | I2: 391035
A3: COGS | B3: 163756 | C3: 161782 | D3: 169559 | E3: 212981 | F3: 223546 | G3: 214137 | H3: 210352 | I3: 216482
A4: Gross Profit | B4: =B2-B3 -> 101839 | C4: =C2-C3 -> 98392 | D4: =D2-D3 -> 104956 | E4: =E2-E3 -> 152836 | F4: =F2-F3 -> 170782 | G4: =G2-G3 -> 169148 | H4: =H2-H3 -> 175251 | I4: =I2-I3 -> 174553
A5: Operating Expenses | B5: 30941 | C5: 34462 | D5: 38668 | E5: 43887 | F5: 51345 | G5: 55292 | H5: 57354 | I5: 59231
A6: Operating Income | B6: 70898 | C6: 63930 | D6: 66288 | E6: 108949 | F6: 119437 | G6: 113856 | H6: 114112 | I6: 115322
A7: Net Income | B7: 59531 | C7: 55256 | D7: 57411 | E7: 94680 | F7: 99803 | G7: 97000 | H7: 97970 | I7: 101004
A8: OCF | B8: 77434 | C8: 69391 | D8: 80674 | E8: 104038 | F8: 122151 | G8: 110543 | H8: 110746 | I8: 113216
A9: CapEx | B9: 13313 | C9: 10495 | D9: 7309 | E9: 11085 | F9: 10708 | G9: 10959 | H9: 10959 | I9: 11482
A10: FCF | B10: =B8-B9 -> 64121 | C10: =C8-C9 -> 58896 | D10: =D8-D9 -> 73365 | E10: =E8-E9 -> 92953 | F10: =F8-F9 -> 111443 | G10: =G8-G9 -> 99584 | H10: =H8-H9 -> 99787 | I10: =I8-I9 -> 101734
A11: Shares Outstanding (post-split) | B11: 19821508000 | C11: 17772944000 | D11: 17102536000 | E11: 16426786000 | F11: 15943425000 | G11: 15550061000 | H11: 15115823000 | I11: 14776353000
A12: Weighted Avg Shares Outstanding (post-split) | B12: 20000436000 | C12: 18470016000 | D12: 17102536000 | E12: 16864919000 | F12: 16215963000 | G12: 15812547000 | H12: 15383000000 | I12: 15021000000
A13: Share Buybacks ($ millions) | B13: 72738 | C13: 66897 | D13: 72358 | E13: 85531 | F13: 89402 | G13: 77550 | H13: 77550 | I13: 79312
A14: Services Revenue | B14: 37190 | C14: 46291 | D14: 53768 | E14: 68425 | F14: 78129 | G14: 85200 | H14: 90300 | I14: 95845
A15: Products Revenue | B15: 228405 | C15: 213883 | D15: 220747 | E15: 297392 | F15: 316199 | G15: 298085 | H15: 295303 | I15: 295193
A16: R&D Expense | B16: 14236 | C16: 16217 | D16: 18752 | E16: 21914 | F16: 26251 | G16: 29915 | H16: 31370 | I16: 33118
A17: SG&A | B17: 16705 | C17: 18245 | D17: 19916 | E17: 21973 | F17: 25094 | G17: 25377 | H17: 25984 | I17: 26113
A18: Total Assets | B18: 365725 | C18: 338516 | D18: 323888 | E18: 351002 | F18: 352755 | G18: 352583 | H18: 364980 | I18: 371284
A19: Total Liabilities | B19: 258578 | C19: 248028 | D19: 258549 | E19: 287912 | F19: 302083 | G19: 290437 | H19: 302090 | I19: 306447
A20: EPS | B20: =B7/(B12/1000000) -> 2.9764851 | C20: =C7/(C12/1000000) -> 2.9916596 | D20: =D7/(D12/1000000) -> 3.3568706 | E20: =E7/(E12/1000000) -> 5.6140204 | F20: =F7/(F12/1000000) -> 6.1546144 | G20: =G7/(G12/1000000) -> 6.1343691 | H20: =H7/(H12/1000000) -> 6.3687187 | I20: =I7/(I12/1000000) -> 6.7241861
A21: FCF per Share | B21: =B10/(B12/1000000) -> 3.2059801 | C21: =C10/(C12/1000000) -> 3.1887357 | D21: =D10/(D12/1000000) -> 4.2897147 | E21: =E10/(E12/1000000) -> 5.5116185 | F21: =F10/(F12/1000000) -> 6.8724256 | G21: =G10/(G12/1000000) -> 6.2977837 | H21: =H10/(H12/1000000) -> 6.4868361 | I21: =I10/(I12/1000000) -> 6.7727848

Sheet Raw_Actuals_Long
A1: Year | B1: Metric | C1: Value
A2: 2018 | B2: Revenue | C2: 265595
A3: 2018 | B3: COGS | C3: 163756
A4: 2018 | B4: Gross Profit | C4: 101839
A5: 2018 | B5: Operating Expenses | C5: 30941
A6: 2018 | B6: Operating Income | C6: 70898
A7: 2019 | B7: Revenue | C7: 260174
A8: 2019 | B8: COGS | C8: 161782
A9: 2019 | B9: Gross Profit | C9: 98392
A10: 2019 | B10: Operating Expenses | C10: 34462
A11: 2019 | B11: Operating Income | C11: 63930
A12: 2020 | B12: Revenue | C12: 274515
A13: 2020 | B13: COGS | C13: 169559
... A41: 2025 | B41: Operating Income | C41: 115322

Sheet Historical_KPIs
A1: Years | B1: 2018 | C1: 2019 | D1: 2020 | E1: 2021 | F1: 2022 | G1: 2023 | H1: 2024 | I1: 2025
A2: Revenue YoY % | B2: N/A | C2: =(Raw_Actuals!C2/Raw_Actuals!B2)-1 -> -0.020410776 | D2: =(Raw_Actuals!D2/Raw_Actuals!C2)-1 -> 0.055120804 | E2: =(Raw_Actuals!E2/Raw_Actuals!D2)-1 -> 0.33259385 | F2: =(Raw_Actuals!F2/Raw_Actuals!E2)-1 -> 0.077937876 | G2: =(Raw_Actuals!G2/Raw_Actuals!F2)-1 -> -0.028004605 | H2: =(Raw_Actuals!H2/Raw_Actuals!G2)-1 -> 0.0060477191 | I2: =(Raw_Actuals!I2/Raw_Actuals!H2)-1 -> 0.014087027
A3: Gross Margin | B3: =Raw_Actuals!B4/Raw_Actuals!B2 -> 0.38343719 | C3: =Raw_Actuals!C4/Raw_Actuals!C2 -> 0.37817768 | D3: =Raw_Actuals!D4/Raw_Actuals!D2 -> 0.38233248 | E3: =Raw_Actuals!E4/Raw_Actuals!E2 -> 0.4177936 | F3: =Raw_Actuals!F4/Raw_Actuals!F2 -> 0.43309631 | G3: =Raw_Actuals!G4/Raw_Actuals!G2 -> 0.4413113 | H3: =Raw_Actuals!H4/Raw_Actuals!H2 -> 0.45448557 | I3: =Raw_Actuals!I4/Raw_Actuals!I2 -> 0.44638715
A4: Operating Margin | B4: =Raw_Actuals!B6/Raw_Actuals!B2 -> 0.26694027 | C4: =Raw_Actuals!C6/Raw_Actuals!C2 -> 0.24572017 | D4: =Raw_Actuals!D6/Raw_Actuals!D2 -> 0.24147314 | E4: =Raw_Actuals!E6/Raw_Actuals!E2 -> 0.29782378 | F4: =Raw_Actuals!F6/Raw_Actuals!F2 -> 0.30288744 | G4: =Raw_Actuals!G6/Raw_Actuals!G2 -> 0.29705311 | H4: =Raw_Actuals!H6/Raw_Actuals!H2 -> 0.29593131 | I4: =Raw_Actuals!I6/Raw_Actuals!I2 -> 0.29491478
A5: Net Margin | B5: =Raw_Actuals!B7/Raw_Actuals!B2 -> 0.22414202 | C5: =Raw_Actuals!C7/Raw_Actuals!C2 -> 0.21238095 | D5: =Raw_Actuals!D7/Raw_Actuals!D2 -> 0.20913611 | E5: =Raw_Actuals!E7/Raw_Actuals!E2 -> 0.25881793 | F5: =Raw_Actuals!F7/Raw_Actuals!F2 -> 0.25309641 | G5: =Raw_Actuals!G7/Raw_Actuals!G2 -> 0.25307539 | H5: =Raw_Actuals!H7/Raw_Actuals!H2 -> 0.2540696 | I5: =Raw_Actuals!I7/Raw_Actuals!I2 -> 0.25829913
A6: FCF Margin | B6: =Raw_Actuals!B10/Raw_Actuals!B2 -> 0.24142397 | C6: =Raw_Actuals!C10/Raw_Actuals!C2 -> 0.22637158 | D6: =Raw_Actuals!D10/Raw_Actuals!D2 -> 0.26725316 | E6: =Raw_Actuals!E10/Raw_Actuals!E2 -> 0.25409699 | F6: =Raw_Actuals!F10/Raw_Actuals!F2 -> 0.28261498 | G6: =Raw_Actuals!G10/Raw_Actuals!G2 -> 0.25981711 | H6: =Raw_Actuals!H10/Raw_Actuals!H2 -> 0.2587817 | I6: =Raw_Actuals!I10/Raw_Actuals!I2 -> 0.26016597
A7: Cash Conversion Ratio | B7: =Raw_Actuals!B8/Raw_Actuals!B7 -> 1.3007341 | C7: =Raw_Actuals!C8/Raw_Actuals!C7 -> 1.2558093 | D7: =Raw_Actuals!D8/Raw_Actuals!D7 -> 1.4052011 | E7: =Raw_Actuals!E8/Raw_Actuals!E7 -> 1.0988382 | F7: =Raw_Actuals!F8/Raw_Actuals!F7 -> 1.2239211 | G7: =Raw_Actuals!G8/Raw_Actuals!G7 -> 1.1396186 | H7: =Raw_Actuals!H8/Raw_Actuals!H7 -> 1.1304073 | I7: =Raw_Actuals!I8/Raw_Actuals!I7 -> 1.1209061
A8: Annual Share Reduction % | B8: N/A | C8: =(Raw_Actuals!B11-Raw_Actuals!C11)/Raw_Actuals!B11 -> 0.10335056 | D8: =(Raw_Actuals!C11-Raw_Actuals!D11)/Raw_Actuals!C11 -> 0.037720706 | E8: =(Raw_Actuals!D11-Raw_Actuals!E11)/Raw_Actuals!D11 -> 0.039511684 | F8: =(Raw_Actuals!E11-Raw_Actuals!F11)/Raw_Actuals!E11 -> 0.029425172 | G8: =(Raw_Actuals!F11-Raw_Actuals!G11)/Raw_Actuals!F11 -> 0.02467249 | H8: =(Raw_Actuals!G11-Raw_Actuals!H11)/Raw_Actuals!G11 -> 0.027925164 | I8: =(Raw_Actuals!H11-Raw_Actuals!I11)/Raw_Actuals!H11 -> 0.022457924
A9: FCF Payout to Buybacks | B9: =Raw_Actuals!B13/Raw_Actuals!B7 -> 1.2218508 | C9: =Raw_Actuals!C13/Raw_Actuals!C7 -> 1.210674 | D9: =Raw_Actuals!D13/Raw_Actuals!D7 -> 1.2603508 | E9: =Raw_Actuals!E13/Raw_Actuals!E7 -> 0.90336924 | F9: =Raw_Actuals!F13/Raw_Actuals!F7 -> 0.8957847 | G9: =Raw_Actuals!G13/Raw_Actuals!G7 -> 0.79948454 | H9: =Raw_Actuals!H13/Raw_Actuals!H7 -> 0.79156885 | I9: =Raw_Actuals!I13/Raw_Actuals!I7 -> 0.78523623
A10: Services % of Revenue | B10: =Raw_Actuals!B14/Raw_Actuals!B2 -> 0.14002523 | C10: =Raw_Actuals!C14/Raw_Actuals!C2 -> 0.17792324 | D10: =Raw_Actuals!D14/Raw_Actuals!D2 -> 0.19586544 | E10: =Raw_Actuals!E14/Raw_Actuals!E2 -> 0.18704708 | F10: =Raw_Actuals!F14/Raw_Actuals!F2 -> 0.19813201 | G10: =Raw_Actuals!G14/Raw_Actuals!G2 -> 0.2222889 | H10: =Raw_Actuals!H14/Raw_Actuals!H2 -> 0.23417868 | I10: =Raw_Actuals!I14/Raw_Actuals!I2 -> 0.24510594
A11: Products % of Revenue | B11: =Raw_Actuals!B15/Raw_Actuals!B2 -> 0.85997477 | C11: =Raw_Actuals!C15/Raw_Actuals!C2 -> 0.82207676 | D11: =Raw_Actuals!D15/Raw_Actuals!D2 -> 0.80413456 | E11: =Raw_Actuals!E15/Raw_Actuals!E2 -> 0.81295292 | F11: =Raw_Actuals!F15/Raw_Actuals!F2 -> 0.80186799 | G11: =Raw_Actuals!G15/Raw_Actuals!G2 -> 0.7777111 | H11: =Raw_Actuals!H15/Raw_Actuals!H2 -> 0.76582132 | I11: =Raw_Actuals!I15/Raw_Actuals!I2 -> 0.75490174
A12: EPS | B12: =Raw_Actuals!B7/(Raw_Actuals!B12/1000000) -> 2.9764851 | C12: =Raw_Actuals!C7/(Raw_Actuals!C12/1000000) -> 2.9916596 | D12: =Raw_Actuals!D7/(Raw_Actuals!D12/1000000) -> 3.3568706 | E12: =Raw_Actuals!E7/(Raw_Actuals!E12/1000000) -> 5.6140204 | F12: =Raw_Actuals!F7/(Raw_Actuals!F12/1000000) -> 6.1546144 | G12: =Raw_Actuals!G7/(Raw_Actuals!G12/1000000) -> 6.1343691 | H12: =Raw_Actuals!H7/(Raw_Actuals!H12/1000000) -> 6.3687187 | I12: =Raw_Actuals!I7/(Raw_Actuals!I12/1000000) -> 6.7241861
A13: FCF per Share | B13: =Raw_Actuals!B10/(Raw_Actuals!B12/1000000) -> 3.2059801 | C13: =Raw_Actuals!C10/(Raw_Actuals!C12/1000000) -> 3.1887357 | D13: =Raw_Actuals!D10/(Raw_Actuals!D12/1000000) -> 4.2897147 | E13: =Raw_Actuals!E10/(Raw_Actuals!E12/1000000) -> 5.5116185 | F13: =Raw_Actuals!F10/(Raw_Actuals!F12/1000000) -> 6.8724256 | G13: =Raw_Actuals!G10/(Raw_Actuals!G12/1000000) -> 6.2977837 | H13: =Raw_Actuals!H10/(Raw_Actuals!H12/1000000) -> 6.4868361 | I13: =Raw_Actuals!I10/(Raw_Actuals!I12/1000000) -> 6.7727848
B17: 2018-2025
A18: Revenue CAGR(2018-2025) | B18: =(Raw_Actuals!I2/Raw_Actuals!B2)^(1/7)-1 -> 0.056816027
A19: Net Income CAGR | B19: =(Raw_Actuals!I7/Raw_Actuals!B7)^(1/7)-1 -> 0.07844833

Sheet Historical_kpis_long
A1: Year | B1: KPI | C1: Value
A2: 2019 | B2: Revenue YoY | C2: -0.0204
A3: 2020 | B3: Revenue YoY | C3: 0.0551
A4: 2021 | B4: Revenue YoY | C4: 0.3326
A5: 2022 | B5: Revenue YoY | C5: 0.0779
A6: 2023 | B6: Revenue YoY | C6: -0.028
A7: 2024 | B7: Revenue YoY | C7: 0.006
A8: 2025 | B8: Revenue YoY | C8: 0.0141
A9: 2018 | B9: Gross Margin | C9: 0.3834
A10: 2019 | B10: Gross Margin | C10: 0.3782
A11: 2020 | B11: Gross Margin | C11: 0.3823
A12: 2021 | B12: Gross Margin | C12: 0.4178
A13: 2022 | B13: Gross Margin | C13: 0.4331
... A24: 2025 | B24: Operating Margin | C24: 0.2949

Sheet Historical_Insights
A1: Insight Title | B1: Insight Text | C1: Key KPI Reference
A2: Growth Reality | B2: Revenue CAGR between 2018 and 2025 is approximately 5.7%, with significant volatility across the period. Following a one-off ~33% surge in 2021, revenue growth normalized to low single digits, confirming Apple’s transition into a mature growth phase rather than a high-growth profile. Consequently, future shareholder returns are more likely to be driven by margin stability, capital returns, and multiple durability than by revenue acceleration. | C2: Revenue CAGR, Revenue YoY
A3: Margin Structure | B3: Gross margin remained around 38% during 2018–2020 but structurally re-rated above 44% from 2021 onward. This expansion appears sustainable and is driven primarily by a richer Services mix and strong pricing power, reinforced by ecosystem lock-in and the scalability of digital services rather than temporary cost reductions. | C3: Gross Margin, Operating Margin
A4: Cash Quality | B4: Apple consistently converts earnings into cash, evidenced by an average free cash flow margin of approximately 26% and operating cash flow conversion persistently above 110%. This highlights high earnings quality and indicates that reported profits are strongly supported by underlying cash generation rather than accounting adjustments. | C4: FCF Margin, OCF Conversion
A5: Capital Allocation Discipline | B5: While buyback intensity has declined from over 110% of free cash flow in 2018–2019 to roughly 78% in recent years, Apple continues to reduce its share count by approximately 2–3% annually. This signals a shift toward a more disciplined and sustainable capital return framework, albeit one that still partially leverages balance sheet flexibility. | C5: Share Reduction %, Buyback Intensity
A6: Business Mix Shift | B6: Services revenue increased from 14% of total revenue in 2018 to approximately 25% in 2025. This structural shift toward recurring, higher-margin revenue streams has been a core driver of margin expansion and materially enhances business resilience across economic cycles. | C6: Services % of Revenue

Sheet 2026_Forecast
A1: Metric | B1: 2025 Actual | C1: Assumption | D1: 2026 Forecast
A2: Revenue – Products | B2: 295193 | C2: Product revenue growth in 2026 is assumed at approximately 1.0%, reflecting the maturity of Apple’s core hardware categories and limited incremental unit growth across developed markets. While selective pricing actions and product refresh cycles provide revenue stability, these are largely offset by market saturation and lengthening replacement cycles. As a result, hardware revenue is modeled as a stabilizing component of the business rather than a primary growth driver. | D2: =B2 * (1 + 1%) -> 298144.93
A3: Revenue – Services | B3: 95845 | C3: Services revenue is expected to grow at approximately 8.0% in 2026, driven by continued expansion of the installed base, higher monetization per user, and increasing adoption of subscription-based offerings. Unlike hardware, Services growth is less dependent on device unit sales and benefits from recurring revenue characteristics, providing greater visibility and durability to top-line performance. | D3: =B3 * (1 + 8%) -> 103512.6
A4: Total Revenue | B4: 391035 | C4: Blended growth driven by Services outpacing Products, resulting in low-to-mid single-digit total revenue growth. | D4: =D2 + D3 -> 401657.53
A5: Gross Margin % | B5: 0.4464 | C5: Gross margin is assumed to remain structurally stable at approximately 44.8% in 2026. The positive contribution from a higher Services mix is expected to broadly offset hardware-related margin pressure from competitive pricing and normalized input costs. No material margin expansion is assumed, reinforcing the conservative and sustainability-focused nature of the forecast. | D5: 0.448
A6: Operating Margin % | B6: 0.2949 | C6: Operating margin in 2026 is modeled at approximately 29.6%, reflecting disciplined cost management rather than incremental operating leverage. Modest revenue growth limits scale benefits, but continued focus on expense control supports margin stability. No structural reduction in OpEx intensity is assumed. | D6: 0.296
A7: Net Margin % | B7: 0.2583 | C7: Net margin in 2026 is assumed to remain broadly stable, reflecting consistent operating profitability, a normalized tax rate, and no material changes in the company’s financing structure. | D7: 0.259
A8: Operating Cash Flow | B8: 113216 | C8: Operating cash flow is assumed at approximately 29% of revenue, consistent with Apple’s historical cash conversion profile. Strong working capital management and the high cash-generative nature of Services support reliable conversion of earnings into cash, reinforcing free cash flow as a robust indicator of underlying economic performance. | D8: =('2026_Forecast'!D4*'2026_Forecast'!D7)*112% -> 116512.82
A9: CapEx | B9: 11482 | C9: Capital expenditures are assumed at approximately 3.0% of revenue in 2026, consistent with a mature business profile. Investment is primarily directed toward infrastructure maintenance and incremental upgrades rather than capacity expansion, supporting strong free cash flow generation. | D9: =B9 * (1 + 5%) -> 12056.1
A10: Free Cash Flow | B10: 101734 | C10: Free cash flow growth in 2026 reflects stable operating margins, disciplined capital spending, and continued high cash conversion, reinforcing Apple’s ability to generate durable shareholder returns. | D10: =D8-D9 -> 104456.72
A11: Share Buybacks | B11: 79312 | C11: Share buybacks in 2026 are modeled as a function of free cash flow rather than a fixed dollar amount. Approximately 78% of free cash flow is assumed to be allocated to share repurchases, consistent with Apple’s long-standing capital return framework. | D11: =D10*78% -> 81476.239
A12: Shares Outstanding | B12: 14766353000 | C12: Continued low single-digit annual reduction driven by sustained buyback activity. | D12: =B12*(1-2.5%) -> 14397194175
A13: EPS | B13: 6.72 | C13: Stable margins and continued share reduction driven by buybacks. | D13: 7.15
A14: Overall 2026 Forecast | B14: N/A | C14: Overall, the 2026 forecast reflects Apple’s evolution into a low-growth but high-durability business, where shareholder value creation is increasingly driven by free cash flow generation and disciplined capital allocation rather than revenue acceleration. | D14: N/A

Sheet Forecast_Summary
A1: Section | B1: Key Takeaway
A2: Revenue Outlook | B2: Total revenue is expected to grow at low-to-mid single-digit rates in 2026, with Services growth acting as the primary driver while Product revenue remains broadly flat in mature hardware markets. Importantly, this mix-driven growth profile enhances revenue durability and visibility, reinforcing Apple’s positioning as a mature, cash-generative business rather than a volume-led growth story.
A3: Margin Outlook | B3: Gross and operating margins are expected to remain structurally elevated, supported by a higher Services mix, ecosystem pricing power, and disciplined cost control. Crucially, margins are not assumed to revert despite normalized revenue growth, suggesting that recent margin strength reflects structural business mix improvements rather than temporary cost relief.
A4: Cash Generation | B4: Cash generation is expected to remain a core strength, with free cash flow sustained above $100bn and operating cash flow conversion continuing to exceed historical averages. This level of cash generation underpins valuation support and positions free cash flow as the primary driver of shareholder returns rather than reported earnings growth.
A5: Capital Allocation | B5: Apple is expected to maintain a disciplined capital return framework, allocating approximately 78% of free cash flow to share buybacks and driving an estimated ~2.5% annual reduction in shares outstanding. In a low-growth revenue environment, this capital return discipline becomes the dominant driver of EPS compounding and per-share value creation.
A6: Risk & Sensitivity | B6: Key downside risks include weaker-than-expected Product demand, a sharper deceleration in Services growth, and margin compression from competitive pricing or elevated investment requirements. From a valuation perspective, sustained Services underperformance or structural margin erosion would represent the most material risks, as they would directly impair free cash flow durability and EPS compounding.
A7: Overall Investment Interpretation | B7: Overall, the 2026 outlook reinforces Apple’s profile as a low-growth but high-durability compounder, where valuation support and shareholder returns are driven primarily by cash generation, margin stability, and disciplined capital allocation rather than revenue re-acceleration.

Sheet Scenario_Analysis
A1: Metric | B1: Bear Case | C1: Base Case | D1: Bull Case
A2: Revenue Growth % | B2: 0.02 | C2: 0.027 | D2: 0.04
A3: Services Growth % | B3: 0.05 | C3: 0.08 | D3: 0.11
A4: Gross Margin % | B4: 0.442 | C4: 0.448 | D4: 0.455
A5: Operating Margin % | B5: 0.288 | C5: 0.296 | D5: 0.305
A6: Free Cash Flow ($bn) | B6: 98 | C6: 104 | D6: 112
A7: Share Buybacks ($bn) | B7: 70 | C7: 81 | D7: 90
A8: Shares Outstanding (bn) | B8: 14.6 | C8: 14.4 | D8: 14.2
A9: EPS | B9: 7 | C9: 7.15 | D9: 7.9
